bus_stop_functions.py
calculate_speed.py
check_punctuality.py
create_bus_coordinates.py
create_bus_stops.py
create_speed_and_coordinates_speed.py
download_bus_stops.py
download_bus_streams.py
webscraping_bus_stops.py
warbusses/__init__.py
warbusses/bus_stop_functions.py
warbusses/calculate_speed.py
warbusses/check_punctuality.py
warbusses/coordinate_functions.py
warbusses/coors_functions.py
warbusses/create_bus_coordinates.py
warbusses/create_bus_stops.py
warbusses/create_speed_and_coordinates_speed.py
warbusses/download_bus_stops.py
warbusses/download_bus_streams.py
warbusses/webscraping_bus_stops.py
warbusses-0.5.dist-info/METADATA
warbusses-0.5.dist-info/WHEEL
warbusses-0.5.dist-info/top_level.txt
warbusses-0.5.dist-info/RECORD
