Metadata-Version: 2.1
Name: warbusses
Version: 0.5
Summary: Useful info about warsaw busses
Home-page: https://github.com/szczor/warbusses
Author: UNKNOWN
Author-email: UNKNOWN
License: UNKNOWN
Platform: UNKNOWN
Classifier: Programming Language :: Python :: 3
